calculator/__init__.py
calculator/calc.py
mycalculator121-0.2.0.dist-info/LICENSE
mycalculator121-0.2.0.dist-info/METADATA
mycalculator121-0.2.0.dist-info/WHEEL
mycalculator121-0.2.0.dist-info/top_level.txt
mycalculator121-0.2.0.dist-info/RECORD
